json_numpy.py
json_numpy-2.1.0.dist-info/LICENSE.txt
json_numpy-2.1.0.dist-info/METADATA
json_numpy-2.1.0.dist-info/WHEEL
json_numpy-2.1.0.dist-info/top_level.txt
json_numpy-2.1.0.dist-info/RECORD
