Metadata-Version: 2.1
Name: json-numpy
Version: 2.1.0
Summary: JSON encoding/decoding for Numpy arrays and scalars
Author-email: Crimson-Crow <github@crimsoncrow.dev>
Maintainer-email: Crimson-Crow <github@crimsoncrow.dev>
License: MIT License
Project-URL: Homepage, https://github.com/Crimson-Crow/json-numpy
Project-URL: Repository, https://github.com/Crimson-Crow/json-numpy.git
Project-URL: Issues, https://github.com/Crimson-Crow/json-numpy/issues
Keywords: json,numpy,serialization,encode,decode,encoding,decoding
Classifier: Development Status :: 5 - Production/Stable
Classifier: Intended Audience :: Developers
Classifier: Intended Audience :: Science/Research
Classifier: Operating System :: OS Independent
Classifier: License :: OSI Approved :: MIT License
Classifier: Programming Language :: Python :: 3
Classifier: Programming Language :: Python :: 3.8
Classifier: Programming Language :: Python :: 3.9
Classifier: Programming Language :: Python :: 3.10
Classifier: Programming Language :: Python :: 3.11
Classifier: Programming Language :: Python :: 3.12
Classifier: Programming Language :: Python :: 3 :: Only
Classifier: Topic :: Utilities
Requires-Python: >=3.8
License-File: LICENSE.txt
Requires-Dist: numpy
